Publish/__init__.py
Publish/gong.py
gong_test_pub-1.0.5.dist-info/LICENSE
gong_test_pub-1.0.5.dist-info/METADATA
gong_test_pub-1.0.5.dist-info/WHEEL
gong_test_pub-1.0.5.dist-info/top_level.txt
gong_test_pub-1.0.5.dist-info/RECORD
